passchek/__init__.py
passchek/passchek.py
passchek-0.2.1.dist-info/LICENSE
passchek-0.2.1.dist-info/METADATA
passchek-0.2.1.dist-info/WHEEL
passchek-0.2.1.dist-info/entry_points.txt
passchek-0.2.1.dist-info/top_level.txt
passchek-0.2.1.dist-info/RECORD
