Metadata-Version: 2.1
Name: passchek
Version: 0.2.1
Summary: Passchek is a simple cli tool, checks if your password has been compromised.
Home-page: https://github.com/edyatl/passchek
Author: Yevgeny Dyatlov
Author-email: edyatl@yandex.ru
License: MIT
Keywords: passchek,password,pwned,troyhunt,github,k-anonymity,interactive,console,sha1,pwnedpassword,versions,virtualenv
Platform: UNKNOWN
Classifier: Programming Language :: Python :: 3
Classifier: Programming Language :: Python :: 3.5
Classifier: Programming Language :: Python :: 3.6
Classifier: Environment :: Console
Classifier: License :: OSI Approved :: MIT License
Classifier: Operating System :: POSIX
Classifier: Intended Audience :: End Users/Desktop
Classifier: Topic :: Utilities
Requires-Python: >=3.5
